{
    "agents": [{
        "id": 41,
        "url": "bjstdmngbgr41.thoughtworks.com",
        "type": "virtual",
        "state": "idle",
        "server": "192.168.229.186",
        "path": "/var/lib/cruise-agent",
        "resources": ["ubuntu", "firefox3", "core-duo"]
    }, {
        "id": 42,
        "url": "bjstdmngbgr42.thoughtworks.com",
        "type": "physical",
        "state": "building",
        "server": "192.168.47.70",
        "path": "/var/lib/cruise-agent",
        "resources": ["ubuntu", "firefox3", "mysql", "core-duo"]
    }, {
        "id": 43,
        "url": "bjstdmngbgr43.thoughtworks.com",
        "type": "virtual",
        "state": "idle",
        "server": "192.168.220.223",
        "path": "/var/lib/cruise-agent",
        "resources": ["ubuntu", "firefox3", "core-duo"]
    }, {
        "id": 44,
        "url": "bjstdmngbgr44.thoughtworks.com",
        "type": "physical",
        "state": "idle",
        "server": "192.168.205.214",
        "path": "/var/lib/cruise-agent",
        "resources": ["ubuntu", "firefox3", "core-duo"]
    }, {
        "id": 45,
        "url": "bjstdmngbgr45.thoughtworks.com",
        "type": "virtual",
        "state": "building",
        "server": "192.168.204.133",
        "path": "/var/lib/cruise-agent",
        "resources": ["ubuntu", "firefox3", "mysql", "core-duo"]
    }, {
        "id": 46,
        "url": "bjstdmngbgr46.thoughtworks.com",
        "type": "physical",
        "state": "idle",
        "server": "192.168.27.255",
        "path": "/var/lib/cruise-agent",
        "resources": ["ubuntu", "firefox3", "core-duo"]
    }, {
        "id": 47,
        "url": "bjstdmngbgr47.thoughtworks.com",
        "type": "virtual",
        "state": "idle",
        "server": "192.168.128.35",
        "path": "/var/lib/cruise-agent",
        "resources": ["ubuntu", "firefox3", "core-duo"]
    }, {
        "id": 48,
        "url": "bjstdmngbgr48.thoughtworks.com",
        "type": "physical",
        "state": "building",
        "server": "192.168.208.234",
        "path": "/var/lib/cruise-agent",
        "resources": ["ubuntu", "firefox3", "mysql", "core-duo"]
    }]
}